{
  "slug": "get",
  "title": "GET",
  "description": "Returns the string value of a key.",
  "docsUrl": "https://redis.io/docs/latest/commands/get/",
  "group": "string",
  "groupLabel": "Strings",
  "syntax": "GET key",
  "complexity": "O(1)",
  "since": "1.0.0",
  "arity": 2,
  "aclCategories": [
    "@read",
    "@string",
    "@fast"
  ],
  "apiMethods": {
    "redis_py": [
      {
        "params": [
          {
            "description": "",
            "name": "name",
            "type": "KeyT"
          }
        ],
        "returns": {
          "description": "",
          "type": "ResponseT"
        },
        "signature": "get(name: KeyT)"
      }
    ],
    "jedis": [
      {
        "params": [
          {
            "description": "",
            "name": "key",
            "type": "String"
          }
        ],
        "returns": {
          "description": "Bulk reply",
          "type": "String"
        },
        "signature": "String get(final String key)"
      }
    ],
    "lettuce_sync": [
      {
        "params": [
          {
            "description": "the key.",
            "name": "key",
            "type": "K"
          }
        ],
        "returns": {
          "description": "V bulk-string-reply the value of key, or null when key does not exist.",
          "type": "V"
        },
        "signature": "V get(K key)"
      }
    ],
    "lettuce_async": [
      {
        "params": [
          {
            "description": "the key.",
            "name": "key",
            "type": "K"
          }
        ],
        "returns": {
          "description": "V bulk-string-reply the value of key, or null when key does not exist.",
          "type": "RedisFuture<V>"
        },
        "signature": "RedisFuture<V> get(K key)"
      }
    ],
    "lettuce_reactive": [
      {
        "params": [
          {
            "description": "the key.",
            "name": "key",
            "type": "K"
          }
        ],
        "returns": {
          "description": "V bulk-string-reply the value of key, or null when key does not exist.",
          "type": "Mono<V>"
        },
        "signature": "Mono<V> get(K key)"
      }
    ],
    "go-redis": [
      {
        "params": [
          {
            "description": "",
            "name": "ctx",
            "type": "context.Context"
          },
          {
            "description": "",
            "name": "key",
            "type": "string"
          }
        ],
        "returns": {
          "description": "",
          "type": "*StringCmd"
        },
        "signature": "Get(ctx context.Context, key string)"
      }
    ],
    "node_redis": [
      {
        "params": [
          {
            "description": "",
            "name": "key",
            "type": "RedisArgument"
          }
        ],
        "returns": {
          "description": "",
          "type": "Any"
        },
        "signature": "GET(key: RedisArgument)"
      }
    ],
    "ioredis": [
      {
        "params": [
          {
            "description": "",
            "name": "key",
            "type": "RedisKey"
          },
          {
            "description": "",
            "name": "callback?",
            "type": "Callback<string | null>"
          }
        ],
        "returns": {
          "description": "",
          "type": "Any"
        },
        "signature": "get(key: RedisKey, callback?: Callback<string | null>)"
      }
    ],
    "redis_rs_sync": [
      {
        "params": [
          {
            "description": "",
            "name": "key",
            "type": "K"
          }
        ],
        "returns": {
          "description": "",
          "type": "(Option<String>)"
        },
        "signature": "get(key: K)"
      },
      {
        "params": [
          {
            "description": "",
            "name": "mut self",
            "type": "Any"
          },
          {
            "description": "",
            "name": "get",
            "type": "bool"
          }
        ],
        "returns": {
          "description": "",
          "type": "Self"
        },
        "signature": "get(mut self, get: bool)"
      }
    ],
    "redis_rs_async": [
      {
        "params": [
          {
            "description": "",
            "name": "key",
            "type": "K"
          }
        ],
        "returns": {
          "description": "",
          "type": "(Option<String>)"
        },
        "signature": "get(key: K)"
      },
      {
        "params": [
          {
            "description": "",
            "name": "mut self",
            "type": "Any"
          },
          {
            "description": "",
            "name": "get",
            "type": "bool"
          }
        ],
        "returns": {
          "description": "",
          "type": "Self"
        },
        "signature": "get(mut self, get: bool)"
      }
    ],
    "nredisstack_sync": [
      {
        "params": [
          {
            "description": "",
            "name": "key",
            "type": "RedisKey"
          },
          {
            "description": "The flags to use for this operation.",
            "name": "flags",
            "type": "CommandFlags"
          }
        ],
        "returns": {
          "description": "The values of the strings with Null for keys do not exist.",
          "type": "RedisValue"
        },
        "signature": "StringGet(RedisKey key, CommandFlags flags = CommandFlags.None)"
      },
      {
        "params": [
          {
            "description": "The keys of the strings.",
            "name": "keys",
            "type": "RedisKey[]"
          },
          {
            "description": "The flags to use for this operation.",
            "name": "flags",
            "type": "CommandFlags"
          }
        ],
        "returns": {
          "description": "The values of the strings with Null for keys do not exist.",
          "type": "RedisValue[]"
        },
        "signature": "StringGet(RedisKey[] keys, CommandFlags flags = CommandFlags.None)"
      },
      {
        "params": [
          {
            "description": "",
            "name": "key",
            "type": "Any"
          },
          {
            "description": "The flags to use for this operation.",
            "name": "flags",
            "type": "Any"
          }
        ],
        "returns": {
          "description": "The values of the strings with Null for keys do not exist.",
          "type": "return"
        },
        "signature": "StringGet(key, flags)"
      },
      {
        "params": [
          {
            "description": "",
            "name": "key",
            "type": "RedisKey"
          },
          {
            "description": "The flags to use for this operation.",
            "name": "flags",
            "type": "CommandFlags"
          }
        ],
        "returns": {
          "description": "The values of the strings with Null for keys do not exist.",
          "type": "RedisValue"
        },
        "signature": "StringGet(RedisKey key, CommandFlags flags = CommandFlags.None)"
      },
      {
        "params": [
          {
            "description": "The keys of the strings.",
            "name": "keys",
            "type": "RedisKey[]"
          },
          {
            "description": "The flags to use for this operation.",
            "name": "flags",
            "type": "CommandFlags"
          }
        ],
        "returns": {
          "description": "The values of the strings with Null for keys do not exist.",
          "type": "RedisValue[]"
        },
        "signature": "StringGet(RedisKey[] keys, CommandFlags flags = CommandFlags.None)"
      }
    ],
    "nredisstack_async": [
      {
        "params": [
          {
            "description": "",
            "name": "key",
            "type": "RedisKey"
          },
          {
            "description": "The flags to use for this operation.",
            "name": "flags",
            "type": "CommandFlags"
          }
        ],
        "returns": {
          "description": "The values of the strings with Null for keys do not exist.",
          "type": "RedisValue"
        },
        "signature": "StringGet(RedisKey key, CommandFlags flags = CommandFlags.None)"
      },
      {
        "params": [
          {
            "description": "The keys of the strings.",
            "name": "keys",
            "type": "RedisKey[]"
          },
          {
            "description": "The flags to use for this operation.",
            "name": "flags",
            "type": "CommandFlags"
          }
        ],
        "returns": {
          "description": "The values of the strings with Null for keys do not exist.",
          "type": "RedisValue[]"
        },
        "signature": "StringGet(RedisKey[] keys, CommandFlags flags = CommandFlags.None)"
      },
      {
        "params": [
          {
            "description": "",
            "name": "key",
            "type": "Any"
          },
          {
            "description": "The flags to use for this operation.",
            "name": "flags",
            "type": "Any"
          }
        ],
        "returns": {
          "description": "The values of the strings with Null for keys do not exist.",
          "type": "return"
        },
        "signature": "StringGet(key, flags)"
      },
      {
        "params": [
          {
            "description": "",
            "name": "key",
            "type": "RedisKey"
          },
          {
            "description": "The flags to use for this operation.",
            "name": "flags",
            "type": "CommandFlags"
          }
        ],
        "returns": {
          "description": "The values of the strings with Null for keys do not exist.",
          "type": "RedisValue"
        },
        "signature": "StringGet(RedisKey key, CommandFlags flags = CommandFlags.None)"
      },
      {
        "params": [
          {
            "description": "The keys of the strings.",
            "name": "keys",
            "type": "RedisKey[]"
          },
          {
            "description": "The flags to use for this operation.",
            "name": "flags",
            "type": "CommandFlags"
          }
        ],
        "returns": {
          "description": "The values of the strings with Null for keys do not exist.",
          "type": "RedisValue[]"
        },
        "signature": "StringGet(RedisKey[] keys, CommandFlags flags = CommandFlags.None)"
      }
    ],
    "php": [
      {
        "params": [
          {
            "description": "",
            "name": "$key",
            "type": "string"
          }
        ],
        "returns": {
          "description": "",
          "type": "string|null"
        },
        "signature": "get(string $key)"
      }
    ],
    "redis_rb": [
      {
        "params": [
          {
            "description": "",
            "name": "key",
            "type": "String"
          }
        ],
        "returns": {
          "description": "",
          "type": "String"
        },
        "signature": "get(key)"
      }
    ]
  },
  "commandFlags": [
    "readonly",
    "fast"
  ],
  "arguments": [
    {
      "display_text": "key",
      "key_spec_index": 0,
      "name": "key",
      "type": "key"
    }
  ],
  "keySpecs": [
    {
      "RO": true,
      "access": true,
      "begin_search": {
        "spec": {
          "index": 1
        },
        "type": "index"
      },
      "find_keys": {
        "spec": {
          "keystep": 1,
          "lastkey": 0,
          "limit": 0
        },
        "type": "range"
      }
    }
  ],
  "redisCategories": [
    "docs",
    "develop",
    "stack",
    "oss",
    "rs",
    "rc",
    "kubernetes",
    "clients"
  ],
  "tableOfContents": {
    "sections": []
  },
  "codeExamples": [],
  "content": "Get the value of `key`.\nIf the key does not exist the special value `nil` is returned.\nAn error is returned if the value stored at `key` is not a string, because `GET`\nonly handles string values.\n\n## Examples\n\n{{% redis-cli %}}\nGET nonexisting\nSET mykey \"Hello\"\nGET mykey\n{{% /redis-cli %}}\n\n### Code examples\n\n{{< clients-example set=\"set_and_get\" step=\"get\" description=\"Foundational: Retrieve the string value of a key using GET (returns nil if key doesn't exist)\" difficulty=\"beginner\" />}}\n\n## Redis Software and Redis Cloud compatibility\n\n| Redis<br />Software | Redis<br />Cloud | <span style=\"min-width: 9em; display: table-cell\">Notes</span> |\n|:----------------------|:-----------------|:------|\n| <span title=\"Supported\">&#x2705; Standard</span><br /><span title=\"Supported\"><nobr>&#x2705; Active-Active</nobr></span> | <span title=\"Supported\">&#x2705; Standard</span><br /><span title=\"Supported\"><nobr>&#x2705; Active-Active</nobr></span> |  |\n\n## Return information\n\n{{< multitabs id=\"get-return-info\" \n    tab1=\"RESP2\" \n    tab2=\"RESP3\" >}}\n\nOne of the following:\n* [Bulk string reply](../../develop/reference/protocol-spec#bulk-strings): the value of the key.\n* [Nil reply](../../develop/reference/protocol-spec#bulk-strings): if the key does not exist.\n\n-tab-sep-\n\nOne of the following:\n* [Bulk string reply](../../develop/reference/protocol-spec#bulk-strings): the value of the key.\n* [Null reply](../../develop/reference/protocol-spec#nulls): key does not exist.\n\n{{< /multitabs >}}",
  "example": "GET nonexisting\nSET mykey \"Hello\"\nGET mykey",
  "intro": "Get the value of `key`.\nIf the key does not exist the special value `nil` is returned.\nAn error is returned if the value stored at `key` is not a string, because `GET`\nonly handles string values.",
  "notes": [],
  "sections": [
    {
      "title": "Overview",
      "level": 1,
      "content": "Get the value of `key`.\nIf the key does not exist the special value `nil` is returned.\nAn error is returned if the value stored at `key` is not a string, because `GET`\nonly handles string values."
    },
    {
      "title": "Examples",
      "level": 2,
      "content": "{{% redis-cli %}}\nGET nonexisting\nSET mykey \"Hello\"\nGET mykey\n{{% /redis-cli %}}"
    },
    {
      "title": "Code examples",
      "level": 3,
      "content": "{{< clients-example set=\"set_and_get\" step=\"get\" description=\"Foundational: Retrieve the string value of a key using GET (returns nil if key doesn't exist)\" difficulty=\"beginner\" />}}"
    },
    {
      "title": "Redis Software and Redis Cloud compatibility",
      "level": 2,
      "content": "| Redis<br />Software | Redis<br />Cloud | <span style=\"min-width: 9em; display: table-cell\">Notes</span> |\n|:----------------------|:-----------------|:------|\n| <span title=\"Supported\">&#x2705; Standard</span><br /><span title=\"Supported\"><nobr>&#x2705; Active-Active</nobr></span> | <span title=\"Supported\">&#x2705; Standard</span><br /><span title=\"Supported\"><nobr>&#x2705; Active-Active</nobr></span> |  |"
    },
    {
      "title": "Return information",
      "level": 2,
      "content": "{{< multitabs id=\"get-return-info\" \n    tab1=\"RESP2\" \n    tab2=\"RESP3\" >}}\n\nOne of the following:\n* [Bulk string reply](../../develop/reference/protocol-spec#bulk-strings): the value of the key.\n* [Nil reply](../../develop/reference/protocol-spec#bulk-strings): if the key does not exist.\n\n-tab-sep-\n\nOne of the following:\n* [Bulk string reply](../../develop/reference/protocol-spec#bulk-strings): the value of the key.\n* [Null reply](../../develop/reference/protocol-spec#nulls): key does not exist.\n\n{{< /multitabs >}}"
    }
  ]
}
